databroker_ls/__init__.py
databroker_ls/_version.py
databroker_ls/command_line.py
databroker_ls/qt.py
databroker_ls/snek.py
databroker_ls/stupid-ls.py
databroker_ls/tests/__init__.py
databroker_ls/tests/conftest.py
databroker_ls/tests/dynamic.py
databroker_ls/tests/test.py
databroker_ls-0.0.3.dist-info/AUTHORS.rst
databroker_ls-0.0.3.dist-info/LICENSE
databroker_ls-0.0.3.dist-info/METADATA
databroker_ls-0.0.3.dist-info/WHEEL
databroker_ls-0.0.3.dist-info/entry_points.txt
databroker_ls-0.0.3.dist-info/top_level.txt
databroker_ls-0.0.3.dist-info/RECORD
