Metadata-Version: 2.1
Name: databroker-ls
Version: 0.0.3
Summary: listing option for databroker
Home-page: https://github.com/claracoo/databroker-ls
Author: Brookhaven National Lab
Author-email: ccook@bnl.gov
License: BSD (3-clause)
Platform: UNKNOWN
Classifier: Development Status :: 2 - Pre-Alpha
Classifier: Natural Language :: English
Classifier: Programming Language :: Python :: 3
Requires-Python: >=3.7
License-File: LICENSE
License-File: AUTHORS.rst
